temp_file_object/__init__.py
temp_file_object/test.py
temp_file_object-0.0.1.dist-info/METADATA
temp_file_object-0.0.1.dist-info/WHEEL
temp_file_object-0.0.1.dist-info/top_level.txt
temp_file_object-0.0.1.dist-info/RECORD
